depq/__init__.py
depq/depq.py
depq/depq_new.py
depq/tests/__init__.py
depq/tests/test_depq.py
depq-1.5.4.dist-info/DESCRIPTION.rst
depq-1.5.4.dist-info/METADATA
depq-1.5.4.dist-info/RECORD
depq-1.5.4.dist-info/WHEEL
depq-1.5.4.dist-info/metadata.json
depq-1.5.4.dist-info/top_level.txt
