Metadata-Version: 2.0
Name: depq
Version: 1.5.4
Summary: Double-ended priority queue
Home-page: https://github.com/Ofekmeister/depq
Author: Ofek Lev
Author-email: ofekmeister@gmail.com
License: MIT
Download-URL: https://github.com/Ofekmeister/depq
Keywords: double ended priority queue,depq,priority queue,data structure,scheduling,heuristic analysis
Platform: UNKNOWN
Classifier: Development Status :: 5 - Production/Stable
Classifier: Intended Audience :: Developers
Classifier: Topic :: Software Development :: Libraries :: Python Modules
Classifier: License :: OSI Approved :: MIT License
Classifier: Natural Language :: English
Classifier: Operating System :: OS Independent
Classifier: Programming Language :: Python :: 2.7
Classifier: Programming Language :: Python :: 3.3
Classifier: Programming Language :: Python :: 3.4
